pyPrintShape/__init__.py
pyPrintShape-0.1.1.dist-info/METADATA
pyPrintShape-0.1.1.dist-info/WHEEL
pyPrintShape-0.1.1.dist-info/top_level.txt
pyPrintShape-0.1.1.dist-info/RECORD
