Metadata-Version: 2.1
Name: pyPrintShape
Version: 0.1.1
Summary: A simple shape printing library
Home-page: https://github.com/code-IM-perfect/pyPrintShapes
Author: Harshit Tomar
Author-email: harshitt345@gmail.com
License: MIT
Classifier: Intended Audience :: Developers
Classifier: License :: OSI Approved :: MIT License
Classifier: Programming Language :: Python
Classifier: Programming Language :: Python :: 3
Classifier: Programming Language :: Python :: 3.6
Classifier: Programming Language :: Python :: 3.7
Classifier: Programming Language :: Python :: 3.8
Classifier: Programming Language :: Python :: 3.9
Classifier: Operating System :: OS Independent
